{
    "backend": "django",
    "db_name": "",
    "db_pass": "",
    "db_type": "sqlite",
    "db_user": "",
    "dbms": "1",
    "description": "generated product",
    "design": "soft-ui-dashboard",
    "docker": "0",
    "err_code": 0,
    "frontend": "",
    "heroku": "0",
    "pattern": "mvc",
    "pro": "0",
    "task_id": "7e968701-1fb7-4723-889c-e4c285f8d726",
    "task_info": "Upload Sources [0%] - 347 files",
    "task_output": "7e968701-1fb7-4723-889c-e4c285f8d726.zip",
    "task_result": "SUCCESS",
    "task_state": "RUNNING",
    "task_ts_end": "2022-12-21-10-22-07",
    "task_ts_start": "2022-12-21-10-22-04"
}